overphloem/__init__.py
overphloem/__main__.py
overphloem-0.1.0.dist-info/METADATA
overphloem-0.1.0.dist-info/WHEEL
overphloem-0.1.0.dist-info/entry_points.txt
overphloem-0.1.0.dist-info/top_level.txt
overphloem-0.1.0.dist-info/RECORD
