Metadata-Version: 2.4
Name: overphloem
Version: 0.1.0
Summary: Framework for writing Overleaf bots
Author: Jordan Matelsky
License: Apache-2.0
Project-URL: Repository, https://github.com/j6k4m8/overphloem
Project-URL: Issues, https://github.com/j6k4m8/overphloem/issues
Requires-Python: >=3.11
